zrlog/__init__.py
zrlog/logger.py
zrlog/logs.py
zrlog-0.3.0.dist-info/LICENSE
zrlog-0.3.0.dist-info/METADATA
zrlog-0.3.0.dist-info/WHEEL
zrlog-0.3.0.dist-info/top_level.txt
zrlog-0.3.0.dist-info/RECORD
