Metadata-Version: 2.1
Name: zrlog
Version: 0.3.0
Summary: Logging with Zirconium-based configuration and supports audit logging
Home-page: https://github.com/turnbullerin/zrlog
Author: Erin Turnbull
Author-email: erin.a.turnbull@gmail.com
Project-URL: Bug Tracker, https://github.com/turnbullerin/zrlog/issues
Classifier: Programming Language :: Python :: 3
Classifier: License :: OSI Approved :: MIT License
Classifier: Operating System :: OS Independent
Requires-Python: >=3.7
License-File: LICENSE
Requires-Dist: zirconium (>=0.2.2)
Requires-Dist: autoinject (>=0.2.1)
Requires-Dist: toml
